pyoptexample/__init__.py
pyoptexample/difference.dll
pyoptexample/difference.so
pyoptexample/operations.py
pyoptexample/sum.dll
pyoptexample/sum.so
pyoptexample-0.2.dist-info/licenses/LICENSE
pyoptexample-0.2.dist-info/METADATA
pyoptexample-0.2.dist-info/WHEEL
pyoptexample-0.2.dist-info/top_level.txt
pyoptexample-0.2.dist-info/RECORD
