Metadata-Version: 2.4
Name: pyoptexample
Version: 0.2
Summary: Practicing optimizing Python with C/C++
Author: Eric J. Drewitz
License: 
Keywords: optimization
Classifier: Programming Language :: Python :: 3
Classifier: License :: OSI Approved :: MIT License
Classifier: Operating System :: OS Independent
Requires-Python: >=3.10
License-File: LICENSE
Dynamic: license-file
